LICENSE.txt
README.md
model_composer/__init__.py
model_composer/_utils.py
model_composer/implementations/__init__.py
model_composer/implementations/tensorflow/__init__.py
model_composer/implementations/tensorflow/composer.py
model_composer/interface.py
model_composer/py.typed
model_composer/spec.py
model_composer-0.3.0.dist-info/LICENSE.txt
model_composer-0.3.0.dist-info/METADATA
model_composer-0.3.0.dist-info/WHEEL
model_composer-0.3.0.dist-info/RECORD
