Metadata-Version: 2.1
Name: model-composer
Version: 0.3.0
Summary: Easily compose a model ensemble from your machine learning models
License: MIT
Author: Marwan Sarieddine
Author-email: sarieddine.marwan@gmail.com
Requires-Python: >=3.8,<3.12
Classifier: License :: OSI Approved :: MIT License
Classifier: Programming Language :: Python :: 3
Classifier: Programming Language :: Python :: 3.8
Classifier: Programming Language :: Python :: 3.9
Classifier: Programming Language :: Python :: 3.10
Classifier: Programming Language :: Python :: 3.11
Provides-Extra: all
Provides-Extra: cloudpathlib
Provides-Extra: tensorflow
Requires-Dist: botocore (>=1.29.155,<2.0.0) ; extra == "cloudpathlib" or extra == "all"
Requires-Dist: cloudpathlib[azure,gs,s3] (>=0.14.0,<0.15.0) ; extra == "cloudpathlib" or extra == "all"
Requires-Dist: pydantic (>=1.10.8,<2.0.0)
Requires-Dist: pydotplus (>=2.0.0,<3.0.0) ; extra == "tensorflow" or extra == "all"
Requires-Dist: pyyaml (>=6.0,<7.0)
Requires-Dist: tensorflow (>=2.0.0,<3.0.0) ; extra == "tensorflow" or extra == "all"
Requires-Dist: typeguard (>=4.0.0,<5.0.0)
